__init__.py
MEDS_Inspect/__init__.py
MEDS_Inspect/__main__.py
MEDS_Inspect/app.py
MEDS_Inspect/code_search.py
MEDS_Inspect/utils.py
MEDS_Inspect/assets/favicon.ico
MEDS_Inspect/assets/MIMIC-IV-DEMO-MEDS/data/held_out/0.parquet
MEDS_Inspect/assets/MIMIC-IV-DEMO-MEDS/data/train/0.parquet
MEDS_Inspect/assets/MIMIC-IV-DEMO-MEDS/data/tuning/0.parquet
MEDS_Inspect/assets/MIMIC-IV-DEMO-MEDS/metadata/.shards.json
MEDS_Inspect/assets/MIMIC-IV-DEMO-MEDS/metadata/codes.parquet
MEDS_Inspect/assets/MIMIC-IV-DEMO-MEDS/metadata/dataset.json
MEDS_Inspect/assets/MIMIC-IV-DEMO-MEDS/metadata/subject_splits.parquet
MEDS_Inspect/assets/MIMIC-IV-DEMO-MEDS/tasks/ICU Mortality first 24h.parquet
MEDS_Inspect/cache/__init__.py
MEDS_Inspect/cache/__main__.py
MEDS_Inspect/cache/cache_results.py
MEDS_Inspect-0.0.9.dist-info/LICENSE
MEDS_Inspect-0.0.9.dist-info/METADATA
MEDS_Inspect-0.0.9.dist-info/WHEEL
MEDS_Inspect-0.0.9.dist-info/entry_points.txt
MEDS_Inspect-0.0.9.dist-info/top_level.txt
MEDS_Inspect-0.0.9.dist-info/RECORD
