Metadata-Version: 2.2
Name: MEDS-Inspect
Version: 0.0.9
Summary: MEDS-Inspect is an interactive data visualization app that supports you in your data exploration.
Author-email: Robin van de Water <robin.vandewater@hpi.de>
Project-URL: Homepage, https://github.com/rvandewater/MEDS-Inpect
Project-URL: Issues, https://github.com/rvandewater/MEDS-Inpect/issues
Classifier: Programming Language :: Python :: 3
Classifier: License :: OSI Approved :: MIT License
Classifier: Operating System :: OS Independent
Requires-Python: >=3.11
License-File: LICENSE
Requires-Dist: polars>=1.15.0
Requires-Dist: dash==2.18.2
Requires-Dist: numpy>=2
Requires-Dist: pandas>=2
Provides-Extra: dev
Requires-Dist: pre-commit<4; extra == "dev"
Provides-Extra: tests
Requires-Dist: pytest; extra == "tests"
Requires-Dist: pytest-cov; extra == "tests"
